curvey/__init__.py
curvey/_typing.py
curvey/approx_medial_axis.py
curvey/blend.py
curvey/curve.py
curvey/curves.py
curvey/edges.py
curvey/flow.py
curvey/plot.py
curvey/polygon.py
curvey/py.typed
curvey/shape_structure_dataset.py
curvey/triangulation.py
curvey/util.py
curvey-0.0.4.dist-info/METADATA
curvey-0.0.4.dist-info/WHEEL
curvey-0.0.4.dist-info/licenses/LICENSE
curvey-0.0.4.dist-info/RECORD
