Metadata-Version: 2.3
Name: curvey
Version: 0.0.4
Summary: Pythonic geometric processing of discrete planar closed curves
Project-URL: Homepage, https://github.com/darikg/curvey/
Project-URL: Documentation, https://darikg.github.io/curvey/
Project-URL: Source Code, https://github.com/darikg/curvey/
Author-email: Darik Gamble <darik.gamble@gmail.com>
Maintainer-email: Darik Gamble <darik.gamble@gmail.com>
License:                    GNU LESSER GENERAL PUBLIC LICENSE
License-File: LICENSE
Keywords: 2d,curvature,curvature flow,curve,geometry,geometry processing,numpy,planar,plotting,shape,shape blending,shape interpolation
Classifier: Development Status :: 4 - Beta
Classifier: Intended Audience :: Science/Research
Classifier: License :: OSI Approved :: GNU Lesser General Public License v3 (LGPLv3)
Classifier: License :: OSI Approved :: MIT License
Classifier: Operating System :: MacOS
Classifier: Operating System :: Microsoft :: Windows
Classifier: Operating System :: POSIX
Classifier: Programming Language :: Python :: 3.9
Classifier: Programming Language :: Python :: 3.10
Classifier: Programming Language :: Python :: 3.11
Classifier: Programming Language :: Python :: 3.12
Classifier: Topic :: Scientific/Engineering :: Information Analysis
Classifier: Topic :: Scientific/Engineering :: Visualization
Requires-Python: >=3.9
Requires-Dist: matplotlib
Requires-Dist: networkx
Requires-Dist: numpy
Requires-Dist: scipy
Requires-Dist: shapely
Requires-Dist: sortedcontainers
Requires-Dist: triangle
Requires-Dist: typing-extensions
Provides-Extra: dev
Requires-Dist: mypy; extra == 'dev'
Requires-Dist: precommit; extra == 'dev'
Requires-Dist: ruff; extra == 'dev'
Requires-Dist: sortedcontainers-stubs; extra == 'dev'
Requires-Dist: sybil; extra == 'dev'
Provides-Extra: docs
Requires-Dist: mkdocs; extra == 'docs'
Requires-Dist: mkdocs-jupyter; extra == 'docs'
Requires-Dist: mkdocs-material; extra == 'docs'
Requires-Dist: mkdocstrings[python]>=0.18; extra == 'docs'
Provides-Extra: test
Requires-Dist: pytest; extra == 'test'
Requires-Dist: sybil; extra == 'test'
